stanhf/__init__.py
stanhf/channel.py
stanhf/cli.py
stanhf/config.py
stanhf/convert.py
stanhf/metadata.py
stanhf/modifier.py
stanhf/pars.py
stanhf/run.py
stanhf/sample.py
stanhf/stanabc.py
stanhf/stanhf.stanfunctions
stanhf/stanstr.py
stanhf/contrib/bfs.py
stanhf/contrib/freq.py
stanhf-1.1.0.dist-info/licenses/LICENSE
stanhf-1.1.0.dist-info/METADATA
stanhf-1.1.0.dist-info/WHEEL
stanhf-1.1.0.dist-info/entry_points.txt
stanhf-1.1.0.dist-info/top_level.txt
stanhf-1.1.0.dist-info/RECORD
