Metadata-Version: 2.4
Name: stanhf
Version: 1.1.0
Author-email: Andrew Fowlie <andrew.j.fowlie@gmail.com>
Classifier: Programming Language :: Python :: 3
Classifier: License :: OSI Approved :: MIT License
Classifier: Operating System :: OS Independent
Requires-Python: >=3.8
License-File: LICENSE
Requires-Dist: arviz
Requires-Dist: matplotlib
Requires-Dist: click
Requires-Dist: click_help_colors
Requires-Dist: cmdstanpy
Requires-Dist: numpy
Requires-Dist: pyhf[contrib]
Dynamic: license-file
